priceit.py
priceit-0.1.7.dist-info/LICENSE
priceit-0.1.7.dist-info/METADATA
priceit-0.1.7.dist-info/WHEEL
priceit-0.1.7.dist-info/top_level.txt
priceit-0.1.7.dist-info/RECORD
