Metadata-Version: 2.1
Name: priceit
Version: 0.1.7
Summary: Data extractor in financial market, including realtime price, history price, financial statements and more. Besides stocks, cryptocurrency is also covered.
Home-page: https://github.com/DavidWang2AI/priceit
Author: David Wang
Author-email: davidwang.2ai@gmail.com
License: MIT
Project-URL: Bug Tracker, https://github.com/DavidWang2AI/priceit/issues
Platform: UNKNOWN
Classifier: Programming Language :: Python :: 3
Classifier: License :: OSI Approved :: MIT License
Classifier: Operating System :: OS Independent
Requires-Python: >=3.6
License-File: LICENSE
Requires-Dist: requests
